streambricks/__init__.py
streambricks/auth/__init__.py
streambricks/auth/decorator.py
streambricks/auth/helpers.py
streambricks/auth/models.py
streambricks/auth/profile_widget.py
streambricks/helpers.py
streambricks/py.typed
streambricks/sidebar.py
streambricks/state.py
streambricks/widgets/__init__.py
streambricks/widgets/bind_kwargs.py
streambricks/widgets/image_capture.py
streambricks/widgets/model_selector.py
streambricks/widgets/model_widget/__init__.py
streambricks/widgets/model_widget/field_metadata_renderers.py
streambricks/widgets/model_widget/main.py
streambricks/widgets/model_widget/type_renderers.py
streambricks/widgets/multi_select.py
streambricks/widgets/sequence.py
streambricks/widgets/type_helpers.py
streambricks-1.0.0.dist-info/WHEEL
streambricks-1.0.0.dist-info/METADATA
streambricks-1.0.0.dist-info/RECORD
