Metadata-Version: 2.3
Name: streambricks
Version: 1.0.0
Summary: Streamlit widgets and helpers
Keywords: 
Author: Philipp Temminghoff
Author-email: Philipp Temminghoff <philipptemminghoff@googlemail.com>
License: MIT License
Classifier: Development Status :: 4 - Beta
Classifier: Intended Audience :: Developers
Classifier: Operating System :: OS Independent
Classifier: Programming Language :: Python :: 3
Classifier: Programming Language :: Python :: 3 :: Only
Classifier: Programming Language :: Python :: 3.12
Classifier: Programming Language :: Python :: 3.13
Classifier: Programming Language :: Python :: 3.14
Classifier: Topic :: Documentation
Classifier: Topic :: Software Development
Classifier: Topic :: Utilities
Classifier: Typing :: Typed
Requires-Dist: fieldz>=0.1.0
Requires-Dist: streamlit>=1.43.2
Requires-Dist: authlib ; extra == 'auth'
Requires-Python: >=3.13
Project-URL: Code coverage, https://app.codecov.io/gh/phil65/streambricks
Project-URL: Discussions, https://github.com/phil65/streambricks/discussions
Project-URL: Documentation, https://phil65.github.io/streambricks/
Project-URL: Issues, https://github.com/phil65/streambricks/issues
Project-URL: Source, https://github.com/phil65/streambricks
Provides-Extra: auth
